LICENSE
abraham_md/__init__.py
abraham_md/config/__init__.py
abraham_md/config/constants.py
abraham_md/config/dialogue.py
abraham_md/config/paths.py
abraham_md/config/structures.py
abraham_md/config/type_annotations.py
abraham_md/generation/__init__.py
abraham_md/generation/module_data_structures.py
abraham_md/generation/module_logic.py
abraham_md/interface/__init__.py
abraham_md/interface/command_line.py
abraham_md/interface/graphical.py
abraham_md/logs/__init__.py
abraham_md/logs/setup_logging.py
abraham_md/main.py
abraham_md/processing/__init__.py
abraham_md/processing/file_conversion.py
abraham_md/processing/file_interaction.py
abraham_md/processing/llm_integration.py
abraham_md/py.typed
abraham_md/templates/overview.md.j2
abraham_md/validation/__init__.py
abraham_md/validation/path_validation.py
abraham_md/VERSION
abraham_md-0.2.0.dist-info/entry_points.txt
abraham_md-0.2.0.dist-info/LICENSE
abraham_md-0.2.0.dist-info/METADATA
abraham_md-0.2.0.dist-info/WHEEL
abraham_md-0.2.0.dist-info/RECORD
