Metadata-Version: 2.1
Name: abraham_md
Version: 0.2.0
Summary: Converts University of Lincoln module files into a useful Obsidian Vault for keeping notes throughout the academic year, as well as revising at the end of an academic year.
Home-page: https://github.com/unkokaeru/abraham_md
License: MIT
Author: W. Fayers
Author-email: wills@fayers.com
Requires-Python: >=3.8,<4.0
Classifier: License :: OSI Approved :: MIT License
Classifier: Programming Language :: Python :: 3
Classifier: Programming Language :: Python :: 3.8
Classifier: Programming Language :: Python :: 3.9
Classifier: Programming Language :: Python :: 3.10
Classifier: Programming Language :: Python :: 3.11
Classifier: Programming Language :: Python :: 3.12
Provides-Extra: dev
Provides-Extra: devlint
Provides-Extra: docs
Provides-Extra: lint
Provides-Extra: release
Provides-Extra: test
Provides-Extra: types
Requires-Dist: rich (>=12.0.0,<13.0.0)
Project-URL: Repository, https://github.com/unkokaeru/abraham_md
